{"resultsWithRank":[{"Rank":1,"Student Name":"Pawan S","Enrolment Status":"All Good","# of Quests Completed":"2","# of Skill Badges Completed":"2","id":311},{"Rank":2,"Student Name":"VELAN.S","Enrolment Status":"All Good","# of Quests Completed":"2","# of Skill Badges Completed":"0","id":68},{"Rank":2,"Student Name":"Priyadharshan","Enrolment Status":"All Good","# of Quests Completed":"1","# of Skill Badges Completed":"1","id":188},{"Rank":2,"Student Name":"Keerthiga.B","Enrolment Status":"All Good","# of Quests Completed":"2","# of Skill Badges Completed":"0","id":231},{"Rank":2,"Student Name":"Vivek Kumar","Enrolment Status":"All Good","# of Quests Completed":"1","# of Skill Badges Completed":"1","id":303},{"Rank":3,"Student Name":"Tharanginee","Enrolment Status":"All Good","# of Quests Completed":"1","# of Skill Badges Completed":"0","id":70},{"Rank":3,"Student Name":"PATRICK PAVITHRAN. G","Enrolment Status":"All Good","# of Quests Completed":"1","# of Skill Badges Completed":"0","id":227},{"Rank":3,"Student Name":"Thananya","Enrolment Status":"All Good","# of Quests Completed":"1","# of Skill Badges Completed":"0","id":228},{"Rank":3,"Student Name":"Yuthika.P","Enrolment Status":"All Good","# of Quests Completed":"1","# of Skill Badges Completed":"0","id":295},{"Rank":4,"Student Name":"Kevin Yehezkiel Gurning","Enrolment Status":"All Good","# of Quests Completed":"0","# of Skill Badges Completed":"0","id":0},{"Rank":5,"Student Name":"BARATHRAJ S","Enrolment Status":"All Good","# of Quests Completed":"0","# of Skill Badges Completed":"0","id":1},{"Rank":6,"Student Name":"YASH SANJAY CHAINANI","Enrolment Status":"All Good","# of Quests Completed":"0","# of Skill Badges Completed":"0","id":2},{"Rank":7,"Student Name":"Tejas Saraf","Enrolment Status":"All Good","# of Quests Completed":"0","# of Skill Badges Completed":"0","id":3},{"Rank":8,"Student Name":"Deepanathan","Enrolment Status":"All Good","# of Quests Completed":"0","# of Skill Badges Completed":"0","id":4},{"Rank":9,"Student Name":"TALOLE ABHAY SANJAY","Enrolment Status":"All Good","# of Quests Completed":"0","# of Skill Badges Completed":"0","id":5},{"Rank":10,"Student Name":"Vishnu priyan.E","Enrolment Status":"All Good","# of Quests Completed":"0","# of Skill Badges Completed":"0","id":6},{"Rank":11,"Student Name":"Samiksha Sanjay Kadam","Enrolment Status":"All Good","# of Quests Completed":"0","# of Skill Badges Completed":"0","id":7},{"Rank":12,"Student Name":"BARATHRAJ S","Enrolment Status":"All Good","# of Quests Completed":"0","# of Skill Badges Completed":"0","id":8},{"Rank":13,"Student Name":"Sameer Rajendra Yadav","Enrolment Status":"All Good","# of Quests Completed":"0","# of Skill Badges Completed":"0","id":9},{"Rank":14,"Student Name":"Ishaan Bais","Enrolment Status":"All Good","# of Quests Completed":"0","# of Skill Badges Completed":"0","id":10},{"Rank":15,"Student Name":"Rahul Gandhi AM","Enrolment Status":"All Good","# of Quests Completed":"0","# of Skill Badges Completed":"0","id":11},{"Rank":16,"Student Name":"Harish Bhaskaran","Enrolment Status":"All Good","# of Quests Completed":"0","# of Skill Badges Completed":"0","id":12},{"Rank":17,"Student Name":"Gayathri sundaresan","Enrolment Status":"All Good","# of Quests Completed":"0","# of Skill Badges Completed":"0","id":13},{"Rank":18,"Student Name":"Harini.P","Enrolment Status":"Wrong Google Cloud Skills Boost Public Profile URL","# of Quests Completed":"0","# of Skill Badges Completed":"0","id":14},{"Rank":19,"Student Name":"Vigneshwaran","Enrolment Status":"Wrong Google Cloud Skills Boost Public Profile URL","# of Quests Completed":"0","# of Skill Badges Completed":"0","id":15},{"Rank":20,"Student Name":"Mohanraj Rajasimman","Enrolment Status":"All Good","# of Quests Completed":"0","# of Skill Badges Completed":"0","id":16},{"Rank":21,"Student Name":"Muthu Kumaran A","Enrolment Status":"Wrong Google Cloud Skills Boost Public Profile URL","# of Quests Completed":"0","# of Skill Badges Completed":"0","id":17},{"Rank":22,"Student Name":"Atchudhan S","Enrolment Status":"All Good","# of Quests Completed":"0","# of Skill Badges Completed":"0","id":18},{"Rank":23,"Student Name":"D.ARJUN","Enrolment Status":"All Good","# of Quests Completed":"0","# of Skill Badges Completed":"0","id":19},{"Rank":24,"Student Name":"Isairekha B","Enrolment Status":"All Good","# of Quests Completed":"0","# of Skill Badges Completed":"0","id":20},{"Rank":25,"Student Name":"Prabalesh P","Enrolment Status":"All Good","# of Quests Completed":"0","# of Skill Badges Completed":"0","id":21},{"Rank":26,"Student Name":"FERON AROCKIAM.S","Enrolment Status":"All Good","# of Quests Completed":"0","# of Skill Badges Completed":"0","id":22},{"Rank":27,"Student Name":"Anupriya. R","Enrolment Status":"All Good","# of Quests Completed":"0","# of Skill Badges Completed":"0","id":23},{"Rank":28,"Student Name":"AKAASH R","Enrolment Status":"All Good","# of Quests Completed":"0","# of Skill Badges Completed":"0","id":24},{"Rank":29,"Student Name":"Akshay Kumar","Enrolment Status":"All Good","# of Quests Completed":"0","# of Skill Badges Completed":"0","id":25},{"Rank":30,"Student Name":"LAVANYA B","Enrolment Status":"All Good","# of Quests Completed":"0","# of Skill Badges Completed":"0","id":26},{"Rank":31,"Student Name":"Manoj Kiran.D","Enrolment Status":"All Good","# of Quests Completed":"0","# of Skill Badges Completed":"0","id":27},{"Rank":32,"Student Name":"Naresh","Enrolment Status":"All Good","# of Quests Completed":"0","# of Skill Badges Completed":"0","id":28},{"Rank":33,"Student Name":"VIGNESH","Enrolment Status":"All Good","# of Quests Completed":"0","# of Skill Badges Completed":"0","id":29},{"Rank":34,"Student Name":"Manibala.V","Enrolment Status":"All Good","# of Quests Completed":"0","# of Skill Badges Completed":"0","id":30},{"Rank":35,"Student Name":"VISAKAN V","Enrolment Status":"All Good","# of Quests Completed":"0","# of Skill Badges Completed":"0","id":31},{"Rank":36,"Student Name":"Rajaram","Enrolment Status":"All Good","# of Quests Completed":"0","# of Skill Badges Completed":"0","id":32},{"Rank":37,"Student Name":"Sathish v","Enrolment Status":"All Good","# of Quests Completed":"0","# of Skill Badges Completed":"0","id":33},{"Rank":38,"Student Name":"Pravina","Enrolment Status":"All Good","# of Quests Completed":"0","# of Skill Badges Completed":"0","id":34},{"Rank":39,"Student Name":"MOHAMMED FEROZ","Enrolment Status":"All Good","# of Quests Completed":"0","# of Skill Badges Completed":"0","id":35},{"Rank":40,"Student Name":"Harish bhalaa s","Enrolment Status":"All Good","# of Quests Completed":"0","# of Skill Badges Completed":"0","id":36},{"Rank":41,"Student Name":"Keerthy Vasan","Enrolment Status":"All Good","# of Quests Completed":"0","# of Skill Badges Completed":"0","id":37},{"Rank":42,"Student Name":"PUNITHAN.M","Enrolment Status":"All Good","# of Quests Completed":"0","# of Skill Badges Completed":"0","id":38},{"Rank":43,"Student Name":"Ahmed Almas.F","Enrolment Status":"All Good","# of Quests Completed":"0","# of Skill Badges Completed":"0","id":39},{"Rank":44,"Student Name":"Suganya","Enrolment Status":"All Good","# of Quests Completed":"0","# of Skill Badges Completed":"0","id":40},{"Rank":45,"Student Name":"PRETHEBHA M","Enrolment Status":"All Good","# of Quests Completed":"0","# of Skill Badges Completed":"0","id":41},{"Rank":46,"Student Name":"ARTHI.M","Enrolment Status":"All Good","# of Quests Completed":"0","# of Skill Badges Completed":"0","id":42},{"Rank":47,"Student Name":"Patrick Pavithran","Enrolment Status":"All Good","# of Quests Completed":"0","# of Skill Badges Completed":"0","id":43},{"Rank":48,"Student Name":"S. Janane","Enrolment Status":"All Good","# of Quests Completed":"0","# of Skill Badges Completed":"0","id":44},{"Rank":49,"Student Name":"Balaji R","Enrolment Status":"All Good","# of Quests Completed":"0","# of Skill Badges Completed":"0","id":45},{"Rank":50,"Student Name":"EZHIL KUMARAN B","Enrolment Status":"All Good","# of Quests Completed":"0","# of Skill Badges Completed":"0","id":46},{"Rank":51,"Student Name":"PRANAVESH S","Enrolment Status":"All Good","# of Quests Completed":"0","# of Skill Badges Completed":"0","id":47},{"Rank":52,"Student Name":"Srimathi.R","Enrolment Status":"Wrong Google Cloud Skills Boost Public Profile URL","# of Quests Completed":"0","# of Skill Badges Completed":"0","id":48},{"Rank":53,"Student Name":"VAITHEESHVAR @ SATYAPRAKASH A T","Enrolment Status":"All Good","# of Quests Completed":"0","# of Skill Badges Completed":"0","id":49},{"Rank":54,"Student Name":"Subashini","Enrolment Status":"All Good","# of Quests Completed":"0","# of Skill Badges Completed":"0","id":50},{"Rank":55,"Student Name":"Yuvanthikhaa","Enrolment Status":"All Good","# of Quests Completed":"0","# of Skill Badges Completed":"0","id":51},{"Rank":56,"Student Name":"Keerthanaa","Enrolment Status":"All Good","# of Quests Completed":"0","# of Skill Badges Completed":"0","id":52},{"Rank":57,"Student Name":"Selvi M","Enrolment Status":"All Good","# of Quests Completed":"0","# of Skill Badges Completed":"0","id":53},{"Rank":58,"Student Name":"N.VINOTHKUMAR","Enrolment Status":"All Good","# of Quests Completed":"0","# of Skill Badges Completed":"0","id":54},{"Rank":59,"Student Name":"Preetha A","Enrolment Status":"All Good","# of Quests Completed":"0","# of Skill Badges Completed":"0","id":55},{"Rank":60,"Student Name":"Hema Arularasi M","Enrolment Status":"All Good","# of Quests Completed":"0","# of Skill Badges Completed":"0","id":56},{"Rank":61,"Student Name":"Priyadharshani","Enrolment Status":"All Good","# of Quests Completed":"0","# of Skill Badges Completed":"0","id":57},{"Rank":62,"Student Name":"Abimanyu R","Enrolment Status":"All Good","# of Quests Completed":"0","# of Skill Badges Completed":"0","id":58},{"Rank":63,"Student Name":"SURYA.R","Enrolment Status":"All Good","# of Quests Completed":"0","# of Skill Badges Completed":"0","id":59},{"Rank":64,"Student Name":"SANJAY N","Enrolment Status":"All Good","# of Quests Completed":"0","# of Skill Badges Completed":"0","id":60},{"Rank":65,"Student Name":"Varsha.V","Enrolment Status":"All Good","# of Quests Completed":"0","# of Skill Badges Completed":"0","id":61},{"Rank":66,"Student Name":"Kalaiarasan Senthil","Enrolment Status":"All Good","# of Quests Completed":"0","# of Skill Badges Completed":"0","id":62},{"Rank":67,"Student Name":"Sivapriyan M","Enrolment Status":"All Good","# of Quests Completed":"0","# of Skill Badges Completed":"0","id":63},{"Rank":68,"Student Name":"Nancy Dhivya .G","Enrolment Status":"All Good","# of Quests Completed":"0","# of Skill Badges Completed":"0","id":64},{"Rank":69,"Student Name":"Aravindhan","Enrolment Status":"All Good","# of Quests Completed":"0","# of Skill Badges Completed":"0","id":65},{"Rank":70,"Student Name":"Hemachandran. S","Enrolment Status":"All Good","# of Quests Completed":"0","# of Skill Badges Completed":"0","id":66},{"Rank":71,"Student Name":"SHASTEESWARAN RAVIANAND THARMIYA","Enrolment Status":"All Good","# of Quests Completed":"0","# of Skill Badges Completed":"0","id":67},{"Rank":72,"Student Name":"Harii Saravanan A","Enrolment Status":"All Good","# of Quests Completed":"0","# of Skill Badges Completed":"0","id":69},{"Rank":73,"Student Name":"Abitha. S","Enrolment Status":"All Good","# of Quests Completed":"0","# of Skill Badges Completed":"0","id":71},{"Rank":74,"Student Name":"LEKA SHREE.E","Enrolment Status":"All Good","# of Quests Completed":"0","# of Skill Badges Completed":"0","id":72},{"Rank":75,"Student Name":"VIJAYSURYA M","Enrolment Status":"All Good","# of Quests Completed":"0","# of Skill Badges Completed":"0","id":73},{"Rank":76,"Student Name":"R.SHIVAPRASANNA","Enrolment Status":"All Good","# of Quests Completed":"0","# of Skill Badges Completed":"0","id":74},{"Rank":77,"Student Name":"Bhuvaneshwaran_G","Enrolment Status":"All Good","# of Quests Completed":"0","# of Skill Badges Completed":"0","id":75},{"Rank":78,"Student Name":"E SWETTHA","Enrolment Status":"All Good","# of Quests Completed":"0","# of Skill Badges Completed":"0","id":76},{"Rank":79,"Student Name":"Tarun V","Enrolment Status":"All Good","# of Quests Completed":"0","# of Skill Badges Completed":"0","id":77},{"Rank":80,"Student Name":"VAITHIYANATHAN.K","Enrolment Status":"All Good","# of Quests Completed":"0","# of Skill Badges Completed":"0","id":78},{"Rank":81,"Student Name":"Rohit SK","Enrolment Status":"All Good","# of Quests Completed":"0","# of Skill Badges Completed":"0","id":79},{"Rank":82,"Student Name":"FAMILA BEGAM. M","Enrolment Status":"All Good","# of Quests Completed":"0","# of Skill Badges Completed":"0","id":80},{"Rank":83,"Student Name":"sowmiya.R","Enrolment Status":"All Good","# of Quests Completed":"0","# of Skill Badges Completed":"0","id":81},{"Rank":84,"Student Name":"Vidhun Siddharth S","Enrolment Status":"All Good","# of Quests Completed":"0","# of Skill Badges Completed":"0","id":82},{"Rank":85,"Student Name":"Harini A","Enrolment Status":"All Good","# of Quests Completed":"0","# of Skill Badges Completed":"0","id":83},{"Rank":86,"Student Name":"DEEPAK P","Enrolment Status":"All Good","# of Quests Completed":"0","# of Skill Badges Completed":"0","id":84},{"Rank":87,"Student Name":"Archana devi C.N","Enrolment Status":"Wrong Google Cloud Skills Boost Public Profile URL","# of Quests Completed":"0","# of Skill Badges Completed":"0","id":85},{"Rank":88,"Student Name":"ABHINAV B","Enrolment Status":"All Good","# of Quests Completed":"0","# of Skill Badges Completed":"0","id":86},{"Rank":89,"Student Name":"Swetha madhan","Enrolment Status":"Wrong Google Cloud Skills Boost Public Profile URL","# of Quests Completed":"0","# of Skill Badges Completed":"0","id":87},{"Rank":90,"Student Name":"SHARAL PRIYA M","Enrolment Status":"All Good","# of Quests Completed":"0","# of Skill Badges Completed":"0","id":88},{"Rank":91,"Student Name":"Deepak naarees G","Enrolment Status":"All Good","# of Quests Completed":"0","# of Skill Badges Completed":"0","id":89},{"Rank":92,"Student Name":"Nimoshini","Enrolment Status":"All Good","# of Quests Completed":"0","# of Skill Badges Completed":"0","id":90},{"Rank":93,"Student Name":"HARISH BHALAA S","Enrolment Status":"All Good","# of Quests Completed":"0","# of Skill Badges Completed":"0","id":91},{"Rank":94,"Student Name":"Jaichandran","Enrolment Status":"All Good","# of Quests Completed":"0","# of Skill Badges Completed":"0","id":92},{"Rank":95,"Student Name":"Hemambuja.S","Enrolment Status":"All Good","# of Quests Completed":"0","# of Skill Badges Completed":"0","id":93},{"Rank":96,"Student Name":"KEERTHESHWARI S","Enrolment Status":"All Good","# of Quests Completed":"0","# of Skill Badges Completed":"0","id":94},{"Rank":97,"Student Name":"Darshan D","Enrolment Status":"All Good","# of Quests Completed":"0","# of Skill Badges Completed":"0","id":95},{"Rank":98,"Student Name":"Aswini.C","Enrolment Status":"All Good","# of Quests Completed":"0","# of Skill Badges Completed":"0","id":96},{"Rank":99,"Student Name":"vijayaprbha.A","Enrolment Status":"All Good","# of Quests Completed":"0","# of Skill Badges Completed":"0","id":97},{"Rank":100,"Student Name":"RAGU.V","Enrolment Status":"All Good","# of Quests Completed":"0","# of Skill Badges Completed":"0","id":98},{"Rank":101,"Student Name":"YAZEEN KHAN .S","Enrolment Status":"All Good","# of Quests Completed":"0","# of Skill Badges Completed":"0","id":99},{"Rank":102,"Student Name":"Vema naga karish Gupta","Enrolment Status":"All Good","# of Quests Completed":"0","# of Skill Badges Completed":"0","id":100},{"Rank":103,"Student Name":"Lingeshwaran G","Enrolment Status":"All Good","# of Quests Completed":"0","# of Skill Badges Completed":"0","id":101},{"Rank":104,"Student Name":"Dheepika Inbaraj","Enrolment Status":"All Good","# of Quests Completed":"0","# of Skill Badges Completed":"0","id":102},{"Rank":105,"Student Name":"RAJ MOHAN .K","Enrolment Status":"All Good","# of Quests Completed":"0","# of Skill Badges Completed":"0","id":103},{"Rank":106,"Student Name":"GOKUL R","Enrolment Status":"All Good","# of Quests Completed":"0","# of Skill Badges Completed":"0","id":104},{"Rank":107,"Student Name":"SELVADHARSHINI R S","Enrolment Status":"All Good","# of Quests Completed":"0","# of Skill Badges Completed":"0","id":105},{"Rank":108,"Student Name":"Dharanya S","Enrolment Status":"All Good","# of Quests Completed":"0","# of Skill Badges Completed":"0","id":106},{"Rank":109,"Student Name":"Balaji S","Enrolment Status":"All Good","# of Quests Completed":"0","# of Skill Badges Completed":"0","id":107},{"Rank":110,"Student Name":"Pranav R","Enrolment Status":"All Good","# of Quests Completed":"0","# of Skill Badges Completed":"0","id":108},{"Rank":111,"Student Name":"Gopinath.R","Enrolment Status":"All Good","# of Quests Completed":"0","# of Skill Badges Completed":"0","id":109},{"Rank":112,"Student Name":"AISWARYA S","Enrolment Status":"All Good","# of Quests Completed":"0","# of Skill Badges Completed":"0","id":110},{"Rank":113,"Student Name":"Sharanjey G","Enrolment Status":"All Good","# of Quests Completed":"0","# of Skill Badges Completed":"0","id":111},{"Rank":114,"Student Name":"Megha shinoj","Enrolment Status":"All Good","# of Quests Completed":"0","# of Skill Badges Completed":"0","id":112},{"Rank":115,"Student Name":"Hirutik R","Enrolment Status":"All Good","# of Quests Completed":"0","# of Skill Badges Completed":"0","id":113},{"Rank":116,"Student Name":"ardra premdas","Enrolment Status":"All Good","# of Quests Completed":"0","# of Skill Badges Completed":"0","id":114},{"Rank":117,"Student Name":"Harish E","Enrolment Status":"All Good","# of Quests Completed":"0","# of Skill Badges Completed":"0","id":115},{"Rank":118,"Student Name":"M.Dharaa","Enrolment Status":"All Good","# of Quests Completed":"0","# of Skill Badges Completed":"0","id":116},{"Rank":119,"Student Name":"Vijay S","Enrolment Status":"All Good","# of Quests Completed":"0","# of Skill Badges Completed":"0","id":117},{"Rank":120,"Student Name":"SANTHANABHARATHI S","Enrolment Status":"All Good","# of Quests Completed":"0","# of Skill Badges Completed":"0","id":118},{"Rank":121,"Student Name":"P.SHIVANIPRIYA","Enrolment Status":"All Good","# of Quests Completed":"0","# of Skill Badges Completed":"0","id":119},{"Rank":122,"Student Name":"shreya saravanane","Enrolment Status":"All Good","# of Quests Completed":"0","# of Skill Badges Completed":"0","id":120},{"Rank":123,"Student Name":"SRIRAM","Enrolment Status":"All Good","# of Quests Completed":"0","# of Skill Badges Completed":"0","id":121},{"Rank":124,"Student Name":"Aabith M.A","Enrolment Status":"All Good","# of Quests Completed":"0","# of Skill Badges Completed":"0","id":122},{"Rank":125,"Student Name":"Prithika.V","Enrolment Status":"All Good","# of Quests Completed":"0","# of Skill Badges Completed":"0","id":123},{"Rank":126,"Student Name":"PARAMESHWARAN .N","Enrolment Status":"Wrong Google Cloud Skills Boost Public Profile URL","# of Quests Completed":"0","# of Skill Badges Completed":"0","id":124},{"Rank":127,"Student Name":"M.SARANYA","Enrolment Status":"All Good","# of Quests Completed":"0","# of Skill Badges Completed":"0","id":125},{"Rank":128,"Student Name":"Gobika. R","Enrolment Status":"All Good","# of Quests Completed":"0","# of Skill Badges Completed":"0","id":126},{"Rank":129,"Student Name":"YOGITHADEVI.V","Enrolment Status":"All Good","# of Quests Completed":"0","# of Skill Badges Completed":"0","id":127},{"Rank":130,"Student Name":"Abirami L","Enrolment Status":"All Good","# of Quests Completed":"0","# of Skill Badges Completed":"0","id":128},{"Rank":131,"Student Name":"LOGESWARAN. S","Enrolment Status":"All Good","# of Quests Completed":"0","# of Skill Badges Completed":"0","id":129},{"Rank":132,"Student Name":"Bhavin Dhanaraj","Enrolment Status":"All Good","# of Quests Completed":"0","# of Skill Badges Completed":"0","id":130},{"Rank":133,"Student Name":"Sowmiya Lakshmi","Enrolment Status":"All Good","# of Quests Completed":"0","# of Skill Badges Completed":"0","id":131},{"Rank":134,"Student Name":"Monish Coumar. S","Enrolment Status":"All Good","# of Quests Completed":"0","# of Skill Badges Completed":"0","id":132},{"Rank":135,"Student Name":"Nivetha.V","Enrolment Status":"All Good","# of Quests Completed":"0","# of Skill Badges Completed":"0","id":133},{"Rank":136,"Student Name":"Thrisha sathish","Enrolment Status":"All Good","# of Quests Completed":"0","# of Skill Badges Completed":"0","id":134},{"Rank":137,"Student Name":"MOULISHWAR VS","Enrolment Status":"All Good","# of Quests Completed":"0","# of Skill Badges Completed":"0","id":135},{"Rank":138,"Student Name":"ANDREW JASON","Enrolment Status":"All Good","# of Quests Completed":"0","# of Skill Badges Completed":"0","id":136},{"Rank":139,"Student Name":"Harshini.k","Enrolment Status":"All Good","# of Quests Completed":"0","# of Skill Badges Completed":"0","id":137},{"Rank":140,"Student Name":"Thalirnila.S","Enrolment Status":"All Good","# of Quests Completed":"0","# of Skill Badges Completed":"0","id":138},{"Rank":141,"Student Name":"HARRESHH M","Enrolment Status":"All Good","# of Quests Completed":"0","# of Skill Badges Completed":"0","id":139},{"Rank":142,"Student Name":"Akshitta","Enrolment Status":"All Good","# of Quests Completed":"0","# of Skill Badges Completed":"0","id":140},{"Rank":143,"Student Name":"GEERTHANA .P","Enrolment Status":"All Good","# of Quests Completed":"0","# of Skill Badges Completed":"0","id":141},{"Rank":144,"Student Name":"Niranjan s","Enrolment Status":"All Good","# of Quests Completed":"0","# of Skill Badges Completed":"0","id":142},{"Rank":145,"Student Name":"Abilash","Enrolment Status":"Wrong Google Cloud Skills Boost Public Profile URL","# of Quests Completed":"0","# of Skill Badges Completed":"0","id":143},{"Rank":146,"Student Name":"Koushik Ananth D","Enrolment Status":"All Good","# of Quests Completed":"0","# of Skill Badges Completed":"0","id":144},{"Rank":147,"Student Name":"Chandrakumar k","Enrolment Status":"All Good","# of Quests Completed":"0","# of Skill Badges Completed":"0","id":145},{"Rank":148,"Student Name":"Abarna.S","Enrolment Status":"All Good","# of Quests Completed":"0","# of Skill Badges Completed":"0","id":146},{"Rank":149,"Student Name":"yogeeswaran","Enrolment Status":"All Good","# of Quests Completed":"0","# of Skill Badges Completed":"0","id":147},{"Rank":150,"Student Name":"Gaayathri M","Enrolment Status":"All Good","# of Quests Completed":"0","# of Skill Badges Completed":"0","id":148},{"Rank":151,"Student Name":"Madhanraj.S","Enrolment Status":"All Good","# of Quests Completed":"0","# of Skill Badges Completed":"0","id":149},{"Rank":152,"Student Name":"BRINDASRI R","Enrolment Status":"Wrong Google Cloud Skills Boost Public Profile URL","# of Quests Completed":"0","# of Skill Badges Completed":"0","id":150},{"Rank":153,"Student Name":"Aravindhan R","Enrolment Status":"All Good","# of Quests Completed":"0","# of Skill Badges Completed":"0","id":151},{"Rank":154,"Student Name":"SAKTHIMALAI P","Enrolment Status":"All Good","# of Quests Completed":"0","# of Skill Badges Completed":"0","id":152},{"Rank":155,"Student Name":"Abhishek Arvind.CB","Enrolment Status":"All Good","# of Quests Completed":"0","# of Skill Badges Completed":"0","id":153},{"Rank":156,"Student Name":"Pavithra M","Enrolment Status":"All Good","# of Quests Completed":"0","# of Skill Badges Completed":"0","id":154},{"Rank":157,"Student Name":"S.abinaya","Enrolment Status":"All Good","# of Quests Completed":"0","# of Skill Badges Completed":"0","id":155},{"Rank":158,"Student Name":"ANNI SHARLEENA . A.B","Enrolment Status":"All Good","# of Quests Completed":"0","# of Skill Badges Completed":"0","id":156},{"Rank":159,"Student Name":"Rahul","Enrolment Status":"All Good","# of Quests Completed":"0","# of Skill Badges Completed":"0","id":157},{"Rank":160,"Student Name":"Archan K Bhalani","Enrolment Status":"All Good","# of Quests Completed":"0","# of Skill Badges Completed":"0","id":158},{"Rank":161,"Student Name":"Banti kumar","Enrolment Status":"All Good","# of Quests Completed":"0","# of Skill Badges Completed":"0","id":159},{"Rank":162,"Student Name":"Anas","Enrolment Status":"Wrong Google Cloud Skills Boost Public Profile URL","# of Quests Completed":"0","# of Skill Badges Completed":"0","id":160},{"Rank":163,"Student Name":"Abu syeed N","Enrolment Status":"All Good","# of Quests Completed":"0","# of Skill Badges Completed":"0","id":161},{"Rank":164,"Student Name":"ASHIKA.S.A","Enrolment Status":"All Good","# of Quests Completed":"0","# of Skill Badges Completed":"0","id":162},{"Rank":165,"Student Name":"T Amirtha Krishnan","Enrolment Status":"All Good","# of Quests Completed":"0","# of Skill Badges Completed":"0","id":163},{"Rank":166,"Student Name":"Soumya.R","Enrolment Status":"Wrong Google Cloud Skills Boost Public Profile URL","# of Quests Completed":"0","# of Skill Badges Completed":"0","id":164},{"Rank":167,"Student Name":"Deepak","Enrolment Status":"All Good","# of Quests Completed":"0","# of Skill Badges Completed":"0","id":165},{"Rank":168,"Student Name":"Lalith Kanth","Enrolment Status":"All Good","# of Quests Completed":"0","# of Skill Badges Completed":"0","id":166},{"Rank":169,"Student Name":"Jayachandran M D","Enrolment Status":"All Good","# of Quests Completed":"0","# of Skill Badges Completed":"0","id":167},{"Rank":170,"Student Name":"Sharan Arvind","Enrolment Status":"All Good","# of Quests Completed":"0","# of Skill Badges Completed":"0","id":168},{"Rank":171,"Student Name":"PAMPANA SURYA NARAYANA MURTHY","Enrolment Status":"All Good","# of Quests Completed":"0","# of Skill Badges Completed":"0","id":169},{"Rank":172,"Student Name":"Sathyanarayanan","Enrolment Status":"All Good","# of Quests Completed":"0","# of Skill Badges Completed":"0","id":170},{"Rank":173,"Student Name":"KEERTHANA G","Enrolment Status":"All Good","# of Quests Completed":"0","# of Skill Badges Completed":"0","id":171},{"Rank":174,"Student Name":"R.Jawahar Chandru","Enrolment Status":"Wrong Google Cloud Skills Boost Public Profile URL","# of Quests Completed":"0","# of Skill Badges Completed":"0","id":172},{"Rank":175,"Student Name":"DHANESHVAR","Enrolment Status":"All Good","# of Quests Completed":"0","# of Skill Badges Completed":"0","id":173},{"Rank":176,"Student Name":"Shri Asikaa S","Enrolment Status":"Wrong Google Cloud Skills Boost Public Profile URL","# of Quests Completed":"0","# of Skill Badges Completed":"0","id":174},{"Rank":177,"Student Name":"Hemapushpavathy K","Enrolment Status":"All Good","# of Quests Completed":"0","# of Skill Badges Completed":"0","id":175},{"Rank":178,"Student Name":"Harini Mourougavel","Enrolment Status":"All Good","# of Quests Completed":"0","# of Skill Badges Completed":"0","id":176},{"Rank":179,"Student Name":"Umar Sheik S","Enrolment Status":"All Good","# of Quests Completed":"0","# of Skill Badges Completed":"0","id":177},{"Rank":180,"Student Name":"Gobinaath","Enrolment Status":"All Good","# of Quests Completed":"0","# of Skill Badges Completed":"0","id":178},{"Rank":181,"Student Name":"S.Jaya Murugan","Enrolment Status":"All Good","# of Quests Completed":"0","# of Skill Badges Completed":"0","id":179},{"Rank":182,"Student Name":"Sivaprrasath.S.J","Enrolment Status":"All Good","# of Quests Completed":"0","# of Skill Badges Completed":"0","id":180},{"Rank":183,"Student Name":"Ananth K","Enrolment Status":"All Good","# of Quests Completed":"0","# of Skill Badges Completed":"0","id":181},{"Rank":184,"Student Name":"SURI.R","Enrolment Status":"All Good","# of Quests Completed":"0","# of Skill Badges Completed":"0","id":182},{"Rank":185,"Student Name":"Aasiya banu.a.j","Enrolment Status":"All Good","# of Quests Completed":"0","# of Skill Badges Completed":"0","id":183},{"Rank":186,"Student Name":"Yuvaraj devaraj","Enrolment Status":"All Good","# of Quests Completed":"0","# of Skill Badges Completed":"0","id":184},{"Rank":187,"Student Name":"Kiransarvesh","Enrolment Status":"All Good","# of Quests Completed":"0","# of Skill Badges Completed":"0","id":185},{"Rank":188,"Student Name":"Joshva Jagan A","Enrolment Status":"All Good","# of Quests Completed":"0","# of Skill Badges Completed":"0","id":186},{"Rank":189,"Student Name":"MOSIKEERAN. T","Enrolment Status":"All Good","# of Quests Completed":"0","# of Skill Badges Completed":"0","id":187},{"Rank":190,"Student Name":"ragul s","Enrolment Status":"All Good","# of Quests Completed":"0","# of Skill Badges Completed":"0","id":189},{"Rank":191,"Student Name":"Jeevitha","Enrolment Status":"All Good","# of Quests Completed":"0","# of Skill Badges Completed":"0","id":190},{"Rank":192,"Student Name":"Sugandan","Enrolment Status":"All Good","# of Quests Completed":"0","# of Skill Badges Completed":"0","id":191},{"Rank":193,"Student Name":"SURUTHY SREE T","Enrolment Status":"All Good","# of Quests Completed":"0","# of Skill Badges Completed":"0","id":192},{"Rank":194,"Student Name":"vijayaraja","Enrolment Status":"All Good","# of Quests Completed":"0","# of Skill Badges Completed":"0","id":193},{"Rank":195,"Student Name":"Hrithika Kristein","Enrolment Status":"All Good","# of Quests Completed":"0","# of Skill Badges Completed":"0","id":194},{"Rank":196,"Student Name":"KIRUTHIKA. C","Enrolment Status":"All Good","# of Quests Completed":"0","# of Skill Badges Completed":"0","id":195},{"Rank":197,"Student Name":"GAANAPATHY SP","Enrolment Status":"All Good","# of Quests Completed":"0","# of Skill Badges Completed":"0","id":196},{"Rank":198,"Student Name":"Deivanai","Enrolment Status":"All Good","# of Quests Completed":"0","# of Skill Badges Completed":"0","id":197},{"Rank":199,"Student Name":"Valar Oli.P","Enrolment Status":"All Good","# of Quests Completed":"0","# of Skill Badges Completed":"0","id":198},{"Rank":200,"Student Name":"sridevi.s","Enrolment Status":"All Good","# of Quests Completed":"0","# of Skill Badges Completed":"0","id":199},{"Rank":201,"Student Name":"KUBENDIRAN","Enrolment Status":"All Good","# of Quests Completed":"0","# of Skill Badges Completed":"0","id":200},{"Rank":202,"Student Name":"Sivabalan.S","Enrolment Status":"All Good","# of Quests Completed":"0","# of Skill Badges Completed":"0","id":201},{"Rank":203,"Student Name":"Naren karthik","Enrolment Status":"All Good","# of Quests Completed":"0","# of Skill Badges Completed":"0","id":202},{"Rank":204,"Student Name":"PARTHIBAN.K","Enrolment Status":"All Good","# of Quests Completed":"0","# of Skill Badges Completed":"0","id":203},{"Rank":205,"Student Name":"S HARINI","Enrolment Status":"All Good","# of Quests Completed":"0","# of Skill Badges Completed":"0","id":204},{"Rank":206,"Student Name":"prathiba singaravelu","Enrolment Status":"All Good","# of Quests Completed":"0","# of Skill Badges Completed":"0","id":205},{"Rank":207,"Student Name":"ARAVINDH.B","Enrolment Status":"All Good","# of Quests Completed":"0","# of Skill Badges Completed":"0","id":206},{"Rank":208,"Student Name":"Aiswarya AV","Enrolment Status":"All Good","# of Quests Completed":"0","# of Skill Badges Completed":"0","id":207},{"Rank":209,"Student Name":"Priyan Sabarish","Enrolment Status":"All Good","# of Quests Completed":"0","# of Skill Badges Completed":"0","id":208},{"Rank":210,"Student Name":"Kavin","Enrolment Status":"All Good","# of Quests Completed":"0","# of Skill Badges Completed":"0","id":209},{"Rank":211,"Student Name":"Amita C","Enrolment Status":"All Good","# of Quests Completed":"0","# of Skill Badges Completed":"0","id":210},{"Rank":212,"Student Name":"Raagavarshini","Enrolment Status":"All Good","# of Quests Completed":"0","# of Skill Badges Completed":"0","id":211},{"Rank":213,"Student Name":"Swathy","Enrolment Status":"All Good","# of Quests Completed":"0","# of Skill Badges Completed":"0","id":212},{"Rank":214,"Student Name":"Harshavardhan","Enrolment Status":"All Good","# of Quests Completed":"0","# of Skill Badges Completed":"0","id":213},{"Rank":215,"Student Name":"Santhana Gopalan G","Enrolment Status":"All Good","# of Quests Completed":"0","# of Skill Badges Completed":"0","id":214},{"Rank":216,"Student Name":"karthick c","Enrolment Status":"All Good","# of Quests Completed":"0","# of Skill Badges Completed":"0","id":215},{"Rank":217,"Student Name":"niranjan kumar","Enrolment Status":"All Good","# of Quests Completed":"0","# of Skill Badges Completed":"0","id":216},{"Rank":218,"Student Name":"INDUMATHI B","Enrolment Status":"All Good","# of Quests Completed":"0","# of Skill Badges Completed":"0","id":217},{"Rank":219,"Student Name":"PRITHIVRAJ","Enrolment Status":"All Good","# of Quests Completed":"0","# of Skill Badges Completed":"0","id":218},{"Rank":220,"Student Name":"Ghayatri C","Enrolment Status":"All Good","# of Quests Completed":"0","# of Skill Badges Completed":"0","id":219},{"Rank":221,"Student Name":"Selvendiran.N","Enrolment Status":"All Good","# of Quests Completed":"0","# of Skill Badges Completed":"0","id":220},{"Rank":222,"Student Name":"S.Nishanth","Enrolment Status":"All Good","# of Quests Completed":"0","# of Skill Badges Completed":"0","id":221},{"Rank":223,"Student Name":"VEDHA.K","Enrolment Status":"All Good","# of Quests Completed":"0","# of Skill Badges Completed":"0","id":222},{"Rank":224,"Student Name":"Adithyan A","Enrolment Status":"All Good","# of Quests Completed":"0","# of Skill Badges Completed":"0","id":223},{"Rank":225,"Student Name":"SUSHANT","Enrolment Status":"All Good","# of Quests Completed":"0","# of Skill Badges Completed":"0","id":224},{"Rank":226,"Student Name":"Sudhaarshan R","Enrolment Status":"All Good","# of Quests Completed":"0","# of Skill Badges Completed":"0","id":225},{"Rank":227,"Student Name":"Dharnika B","Enrolment Status":"All Good","# of Quests Completed":"0","# of Skill Badges Completed":"0","id":226},{"Rank":228,"Student Name":"AATIF AHAMED J","Enrolment Status":"All Good","# of Quests Completed":"0","# of Skill Badges Completed":"0","id":229},{"Rank":229,"Student Name":"Muthu Kumaran A","Enrolment Status":"All Good","# of Quests Completed":"0","# of Skill Badges Completed":"0","id":230},{"Rank":230,"Student Name":"Dheepika C","Enrolment Status":"All Good","# of Quests Completed":"0","# of Skill Badges Completed":"0","id":232},{"Rank":231,"Student Name":"Diwaakaran Palaniraj","Enrolment Status":"All Good","# of Quests Completed":"0","# of Skill Badges Completed":"0","id":233},{"Rank":232,"Student Name":"B.M.Somesh","Enrolment Status":"All Good","# of Quests Completed":"0","# of Skill Badges Completed":"0","id":234},{"Rank":233,"Student Name":"SONIA.C","Enrolment Status":"All Good","# of Quests Completed":"0","# of Skill Badges Completed":"0","id":235},{"Rank":234,"Student Name":"Harini B","Enrolment Status":"All Good","# of Quests Completed":"0","# of Skill Badges Completed":"0","id":236},{"Rank":235,"Student Name":"Mohanaprasanth.S","Enrolment Status":"All Good","# of Quests Completed":"0","# of Skill Badges Completed":"0","id":237},{"Rank":236,"Student Name":"Mahalakshmi R","Enrolment Status":"All Good","# of Quests Completed":"0","# of Skill Badges Completed":"0","id":238},{"Rank":237,"Student Name":"Harshinee","Enrolment Status":"All Good","# of Quests Completed":"0","# of Skill Badges Completed":"0","id":239},{"Rank":238,"Student Name":"Farhaana","Enrolment Status":"All Good","# of Quests Completed":"0","# of Skill Badges Completed":"0","id":240},{"Rank":239,"Student Name":"Dhivyaprabha V","Enrolment Status":"All Good","# of Quests Completed":"0","# of Skill Badges Completed":"0","id":241},{"Rank":240,"Student Name":"Seeman","Enrolment Status":"Wrong Google Cloud Skills Boost Public Profile URL","# of Quests Completed":"0","# of Skill Badges Completed":"0","id":242},{"Rank":241,"Student Name":"Naveenkumar","Enrolment Status":"All Good","# of Quests Completed":"0","# of Skill Badges Completed":"0","id":243},{"Rank":242,"Student Name":"C.Vasan","Enrolment Status":"All Good","# of Quests Completed":"0","# of Skill Badges Completed":"0","id":244},{"Rank":243,"Student Name":"Mohita V","Enrolment Status":"All Good","# of Quests Completed":"0","# of Skill Badges Completed":"0","id":245},{"Rank":244,"Student Name":"Boomika A","Enrolment Status":"All Good","# of Quests Completed":"0","# of Skill Badges Completed":"0","id":246},{"Rank":245,"Student Name":"Varshini S","Enrolment Status":"All Good","# of Quests Completed":"0","# of Skill Badges Completed":"0","id":247},{"Rank":246,"Student Name":"BABA S","Enrolment Status":"All Good","# of Quests Completed":"0","# of Skill Badges Completed":"0","id":248},{"Rank":247,"Student Name":"SEETHARANI T","Enrolment Status":"All Good","# of Quests Completed":"0","# of Skill Badges Completed":"0","id":249},{"Rank":248,"Student Name":"A.Hari Guptha","Enrolment Status":"All Good","# of Quests Completed":"0","# of Skill Badges Completed":"0","id":250},{"Rank":249,"Student Name":"Keerthiraj C","Enrolment Status":"All Good","# of Quests Completed":"0","# of Skill Badges Completed":"0","id":251},{"Rank":250,"Student Name":"Durgesh Parihar","Enrolment Status":"All Good","# of Quests Completed":"0","# of Skill Badges Completed":"0","id":252},{"Rank":251,"Student Name":"ANANDAGEETHAN R.B","Enrolment Status":"All Good","# of Quests Completed":"0","# of Skill Badges Completed":"0","id":253},{"Rank":252,"Student Name":"Sutharsan s","Enrolment Status":"All Good","# of Quests Completed":"0","# of Skill Badges Completed":"0","id":254},{"Rank":253,"Student Name":"AASHIK. N","Enrolment Status":"All Good","# of Quests Completed":"0","# of Skill Badges Completed":"0","id":255},{"Rank":254,"Student Name":"Mohamed Tawfiq","Enrolment Status":"All Good","# of Quests Completed":"0","# of Skill Badges Completed":"0","id":256},{"Rank":255,"Student Name":"T GOKULNATH","Enrolment Status":"All Good","# of Quests Completed":"0","# of Skill Badges Completed":"0","id":257},{"Rank":256,"Student Name":"Abinav s","Enrolment Status":"All Good","# of Quests Completed":"0","# of Skill Badges Completed":"0","id":258},{"Rank":257,"Student Name":"Sriharish","Enrolment Status":"All Good","# of Quests Completed":"0","# of Skill Badges Completed":"0","id":259},{"Rank":258,"Student Name":"Karthik M","Enrolment Status":"All Good","# of Quests Completed":"0","# of Skill Badges Completed":"0","id":260},{"Rank":259,"Student Name":"Santosh T","Enrolment Status":"All Good","# of Quests Completed":"0","# of Skill Badges Completed":"0","id":261},{"Rank":260,"Student Name":"Shree Lekha.M","Enrolment Status":"All Good","# of Quests Completed":"0","# of Skill Badges Completed":"0","id":262},{"Rank":261,"Student Name":"Sheik Ahamed SD","Enrolment Status":"All Good","# of Quests Completed":"0","# of Skill Badges Completed":"0","id":263},{"Rank":262,"Student Name":"Mugilan V","Enrolment Status":"All Good","# of Quests Completed":"0","# of Skill Badges Completed":"0","id":264},{"Rank":263,"Student Name":"Surender","Enrolment Status":"All Good","# of Quests Completed":"0","# of Skill Badges Completed":"0","id":265},{"Rank":264,"Student Name":"R. Sreekishore Ramesh","Enrolment Status":"All Good","# of Quests Completed":"0","# of Skill Badges Completed":"0","id":266},{"Rank":265,"Student Name":"Ashwanth Prithish .A","Enrolment Status":"All Good","# of Quests Completed":"0","# of Skill Badges Completed":"0","id":267},{"Rank":266,"Student Name":"Abinaya.S","Enrolment Status":"All Good","# of Quests Completed":"0","# of Skill Badges Completed":"0","id":268},{"Rank":267,"Student Name":"Adhvika V","Enrolment Status":"All Good","# of Quests Completed":"0","# of Skill Badges Completed":"0","id":269},{"Rank":268,"Student Name":"R.Bharkavi","Enrolment Status":"All Good","# of Quests Completed":"0","# of Skill Badges Completed":"0","id":270},{"Rank":269,"Student Name":"T N GURURAMAN","Enrolment Status":"All Good","# of Quests Completed":"0","# of Skill Badges Completed":"0","id":271},{"Rank":270,"Student Name":"Mohamed Ashik","Enrolment Status":"All Good","# of Quests Completed":"0","# of Skill Badges Completed":"0","id":272},{"Rank":271,"Student Name":"PATRICK PAVITHRAN","Enrolment Status":"All Good","# of Quests Completed":"0","# of Skill Badges Completed":"0","id":273},{"Rank":272,"Student Name":"Subash Raj M","Enrolment Status":"All Good","# of Quests Completed":"0","# of Skill Badges Completed":"0","id":274},{"Rank":273,"Student Name":"Rahul. S","Enrolment Status":"All Good","# of Quests Completed":"0","# of Skill Badges Completed":"0","id":275},{"Rank":274,"Student Name":"Rohitha nancy A","Enrolment Status":"All Good","# of Quests Completed":"0","# of Skill Badges Completed":"0","id":276},{"Rank":275,"Student Name":"sakthiswarrna.T","Enrolment Status":"All Good","# of Quests Completed":"0","# of Skill Badges Completed":"0","id":277},{"Rank":276,"Student Name":"girahalekshmi.N","Enrolment Status":"All Good","# of Quests Completed":"0","# of Skill Badges Completed":"0","id":278},{"Rank":277,"Student Name":"Naveenraj N","Enrolment Status":"All Good","# of Quests Completed":"0","# of Skill Badges Completed":"0","id":279},{"Rank":278,"Student Name":"ARIVOLI","Enrolment Status":"All Good","# of Quests Completed":"0","# of Skill Badges Completed":"0","id":280},{"Rank":279,"Student Name":"Viswa V","Enrolment Status":"All Good","# of Quests Completed":"0","# of Skill Badges Completed":"0","id":281},{"Rank":280,"Student Name":"Praveen kumar s","Enrolment Status":"All Good","# of Quests Completed":"0","# of Skill Badges Completed":"0","id":282},{"Rank":281,"Student Name":"Kalainidhi S","Enrolment Status":"All Good","# of Quests Completed":"0","# of Skill Badges Completed":"0","id":283},{"Rank":282,"Student Name":"Rokhitha N","Enrolment Status":"All Good","# of Quests Completed":"0","# of Skill Badges Completed":"0","id":284},{"Rank":283,"Student Name":"Vijay suriya","Enrolment Status":"All Good","# of Quests Completed":"0","# of Skill Badges Completed":"0","id":285},{"Rank":284,"Student Name":"Vijay K","Enrolment Status":"All Good","# of Quests Completed":"0","# of Skill Badges Completed":"0","id":286},{"Rank":285,"Student Name":"Aravind Pugazh","Enrolment Status":"All Good","# of Quests Completed":"0","# of Skill Badges Completed":"0","id":287},{"Rank":286,"Student Name":"Anusha. L","Enrolment Status":"All Good","# of Quests Completed":"0","# of Skill Badges Completed":"0","id":288},{"Rank":287,"Student Name":"SABAREESH R","Enrolment Status":"All Good","# of Quests Completed":"0","# of Skill Badges Completed":"0","id":289},{"Rank":288,"Student Name":"Bavadharini S","Enrolment Status":"All Good","# of Quests Completed":"0","# of Skill Badges Completed":"0","id":290},{"Rank":289,"Student Name":"Ashwini Mahendiran","Enrolment Status":"All Good","# of Quests Completed":"0","# of Skill Badges Completed":"0","id":291},{"Rank":290,"Student Name":"shivani umamaheswari k","Enrolment Status":"All Good","# of Quests Completed":"0","# of Skill Badges Completed":"0","id":292},{"Rank":291,"Student Name":"Malinda.D","Enrolment Status":"All Good","# of Quests Completed":"0","# of Skill Badges Completed":"0","id":293},{"Rank":292,"Student Name":"Revanth D","Enrolment Status":"All Good","# of Quests Completed":"0","# of Skill Badges Completed":"0","id":294},{"Rank":293,"Student Name":"S. KIRAN YADAV","Enrolment Status":"All Good","# of Quests Completed":"0","# of Skill Badges Completed":"0","id":296},{"Rank":294,"Student Name":"Yuvaraj E","Enrolment Status":"All Good","# of Quests Completed":"0","# of Skill Badges Completed":"0","id":297},{"Rank":295,"Student Name":"Priyadharshni S","Enrolment Status":"All Good","# of Quests Completed":"0","# of Skill Badges Completed":"0","id":298},{"Rank":296,"Student Name":"Yazhini K","Enrolment Status":"All Good","# of Quests Completed":"0","# of Skill Badges Completed":"0","id":299},{"Rank":297,"Student Name":"Suhas Sunil podey","Enrolment Status":"All Good","# of Quests Completed":"0","# of Skill Badges Completed":"0","id":300},{"Rank":298,"Student Name":"Aastha Himanshu Kiri","Enrolment Status":"All Good","# of Quests Completed":"0","# of Skill Badges Completed":"0","id":301},{"Rank":299,"Student Name":"SANTOSH KUJUR","Enrolment Status":"All Good","# of Quests Completed":"0","# of Skill Badges Completed":"0","id":302},{"Rank":300,"Student Name":"Karthik S","Enrolment Status":"All Good","# of Quests Completed":"0","# of Skill Badges Completed":"0","id":304},{"Rank":301,"Student Name":"Venkat Sriram","Enrolment Status":"All Good","# of Quests Completed":"0","# of Skill Badges Completed":"0","id":305},{"Rank":302,"Student Name":"Debanjan roy","Enrolment Status":"All Good","# of Quests Completed":"0","# of Skill Badges Completed":"0","id":306},{"Rank":303,"Student Name":"vadla manohar","Enrolment Status":"All Good","# of Quests Completed":"0","# of Skill Badges Completed":"0","id":307},{"Rank":304,"Student Name":"DHANA SHREE N","Enrolment Status":"All Good","# of Quests Completed":"0","# of Skill Badges Completed":"0","id":308},{"Rank":305,"Student Name":"Yash Kumar Bansal","Enrolment Status":"All Good","# of Quests Completed":"0","# of Skill Badges Completed":"0","id":309},{"Rank":306,"Student Name":"Sam Joshua.S","Enrolment Status":"All Good","# of Quests Completed":"0","# of Skill Badges Completed":"0","id":310},{"Rank":307,"Student Name":"Gautam raj","Enrolment Status":"All Good","# of Quests Completed":"0","# of Skill Badges Completed":"0","id":312},{"Rank":308,"Student Name":"ANISH MURALIDHARAN","Enrolment Status":"All Good","# of Quests Completed":"0","# of Skill Badges Completed":"0","id":313},{"Rank":309,"Student Name":"Omveer Panwar","Enrolment Status":"All Good","# of Quests Completed":"0","# of Skill Badges Completed":"0","id":314},{"Rank":310,"Student Name":"Piyush Yadav","Enrolment Status":"All Good","# of Quests Completed":"0","# of Skill Badges Completed":"0","id":315},{"Rank":311,"Student Name":"RAMAN VERMA","Enrolment Status":"All Good","# of Quests Completed":"0","# of Skill Badges Completed":"0","id":316},{"Rank":312,"Student Name":"Prashan buccha","Enrolment Status":"All Good","# of Quests Completed":"0","# of Skill Badges Completed":"0","id":317},{"Rank":313,"Student Name":"Soumyadip Das","Enrolment Status":"All Good","# of Quests Completed":"0","# of Skill Badges Completed":"0","id":318},{"Rank":314,"Student Name":"Abhishek","Enrolment Status":"Wrong Google Cloud Skills Boost Public Profile URL","# of Quests Completed":"0","# of Skill Badges Completed":"0","id":319},{"Rank":315,"Student Name":"Shivam Pal","Enrolment Status":"All Good","# of Quests Completed":"0","# of Skill Badges Completed":"0","id":320}],"buildDate":"Wed May 18 2022","institute":"[Referred] Politeknik Siber dan Sandi Negara"}